prefsniff/__about__.py
prefsniff/__init__.py
prefsniff/changetypes.py
prefsniff/exceptions.py
prefsniff/prefsniff.py
prefsniff/version.py
prefsniff-0.3.1.dist-info/LICENSE
prefsniff-0.3.1.dist-info/METADATA
prefsniff-0.3.1.dist-info/WHEEL
prefsniff-0.3.1.dist-info/entry_points.txt
prefsniff-0.3.1.dist-info/top_level.txt
prefsniff-0.3.1.dist-info/RECORD
