Metadata-Version: 2.1
Name: prefsniff
Version: 0.3.1
Summary: macOS defaults(1) command generator
Home-page: https://github.com/zcutlip/prefsniff
Requires-Python: >= 3.7
License-File: LICENSE
Requires-Dist: watchdog >=1.0.2
Requires-Dist: py-dict-repr
